affinidi_tdk_iota_client/__init__.py
affinidi_tdk_iota_client/api/__init__.py
affinidi_tdk_iota_client/api/callback_api.py
affinidi_tdk_iota_client/api/configurations_api.py
affinidi_tdk_iota_client/api/dcql_query_api.py
affinidi_tdk_iota_client/api/default_api.py
affinidi_tdk_iota_client/api/iota_api.py
affinidi_tdk_iota_client/api/pex_query_api.py
affinidi_tdk_iota_client/api_client.py
affinidi_tdk_iota_client/api_response.py
affinidi_tdk_iota_client/configuration.py
affinidi_tdk_iota_client/exceptions.py
affinidi_tdk_iota_client/models/__init__.py
affinidi_tdk_iota_client/models/already_exists_error.py
affinidi_tdk_iota_client/models/aws_exchange_credentials.py
affinidi_tdk_iota_client/models/aws_exchange_credentials_ok.py
affinidi_tdk_iota_client/models/aws_exchange_credentials_project_token.py
affinidi_tdk_iota_client/models/aws_exchange_credentials_project_token_ok.py
affinidi_tdk_iota_client/models/aws_exchange_credentials_project_token_ok_credentials.py
affinidi_tdk_iota_client/models/callback_input.py
affinidi_tdk_iota_client/models/callback_response_ok.py
affinidi_tdk_iota_client/models/consent_dto.py
affinidi_tdk_iota_client/models/cors_aws_exchange_credentials_ok.py
affinidi_tdk_iota_client/models/cors_aws_exchange_credentials_project_token_ok.py
affinidi_tdk_iota_client/models/cors_fetch_iota_vp_response_ok.py
affinidi_tdk_iota_client/models/cors_initiate_data_sharing_request_ok.py
affinidi_tdk_iota_client/models/cors_iot_oidc4vpcallback_ok.py
affinidi_tdk_iota_client/models/cors_iota_exchange_credentials_ok.py
affinidi_tdk_iota_client/models/create_dcql_query_input.py
affinidi_tdk_iota_client/models/create_iota_configuration_input.py
affinidi_tdk_iota_client/models/create_pex_query_input.py
affinidi_tdk_iota_client/models/dcql_query_dto.py
affinidi_tdk_iota_client/models/delete_pex_queries_input.py
affinidi_tdk_iota_client/models/fetch_iotavp_response_input.py
affinidi_tdk_iota_client/models/fetch_iotavp_response_ok.py
affinidi_tdk_iota_client-1.57.0.dist-info/METADATA
affinidi_tdk_iota_client-1.57.0.dist-info/WHEEL
affinidi_tdk_iota_client-1.57.0.dist-info/RECORD
